devtools_open_graph/__init__.py
devtools_open_graph-1.0.1.dist-info/METADATA
devtools_open_graph-1.0.1.dist-info/WHEEL
devtools_open_graph-1.0.1.dist-info/top_level.txt
devtools_open_graph-1.0.1.dist-info/RECORD
