Metadata-Version: 2.1
Name: devtools_open_graph
Version: 1.0.1
Summary: Open Graph meta tags generator
Home-page: https://devtools.at/tools/open-graph-generator
Author: DevTools.at
Author-email: hello@devtools.at
Project-URL: Homepage, https://devtools.at/tools/open-graph-generator
Project-URL: Repository, https://github.com/devtools-at/open-graph-generator
Classifier: Development Status :: 4 - Beta
Classifier: Intended Audience :: Developers
Classifier: License :: OSI Approved :: MIT License
Classifier: Programming Language :: Python :: 3
Requires-Python: >=3.8
